messagebox/__init__.py
messagebox/_dummy.py
messagebox/_linux.py
messagebox/_win32.py
messagebox-0.1.0.dist-info/LICENSE
messagebox-0.1.0.dist-info/METADATA
messagebox-0.1.0.dist-info/WHEEL
messagebox-0.1.0.dist-info/top_level.txt
messagebox-0.1.0.dist-info/RECORD
