Metadata-Version: 2.1
Name: messagebox
Version: 0.1.0
Summary: display messageboxes without library dependency like tkinter
Home-page: https://github.com/PlayerG9/PyMessageBox
Author: PlayerG9
License: UNKNOWN
Project-URL: Author Github, https://github.com/PlayerG9
Project-URL: Bug Tracker, https://github.com/PlayerG9/PyMessageBox/issues
Platform: UNKNOWN
Classifier: Programming Language :: Python :: 3
Classifier: License :: OSI Approved :: MIT License
Classifier: Operating System :: OS Independent
Requires-Python: >=3.6
License-File: LICENSE
